MANIFEST.in
README.md
setup.py
dirutility/__init__.py
dirutility/_version.py
dirutility/backup.py
dirutility/compare.py
dirutility/dump.py
dirutility/error.py
dirutility/ftp.py
dirutility/gui.py
dirutility/hash.py
dirutility/move.py
dirutility/multiprocess.py
dirutility/permissions.py
dirutility/system.py
dirutility/versions.py
dirutility/view.py
dirutility/open/__init__.py
dirutility/open/clazz.py
dirutility/open/open.py
dirutility/walk/__init__.py
dirutility/walk/filter.py
dirutility/walk/multiprocess.py
dirutility/walk/sequential.py
dirutility/walk/walk.py
dirutility_dev.egg-info/PKG-INFO
dirutility_dev.egg-info/SOURCES.txt
dirutility_dev.egg-info/dependency_links.txt
dirutility_dev.egg-info/entry_points.txt
dirutility_dev.egg-info/requires.txt
dirutility_dev.egg-info/top_level.txt